proxylists/__init__.py
proxylists/version.py
proxylists/proxies/__init__.py
proxylists/proxies/connections.py
proxylists/proxies/decodo.py
proxylists/proxies/freeproxy.py
proxylists/proxies/geonode.py
proxylists/proxies/hidemy.py
proxylists/proxies/oxylabs.py
proxylists/proxies/proxydb.py
proxylists/proxies/proxyworld.py
proxylists/proxies/server.py
proxylists/proxies/smart.py
proxylists/proxies/spys.py
proxylists-0.14.2.dist-info/LICENSE
proxylists-0.14.2.dist-info/METADATA
proxylists-0.14.2.dist-info/WHEEL
proxylists-0.14.2.dist-info/top_level.txt
proxylists-0.14.2.dist-info/RECORD
