Metadata-Version: 2.1
Name: proxylists
Version: 0.14.2
Summary: Package for getting useful proxy servers, can use lists like hidemy or proxydb.
Home-page: https://github.com/phenobarbital/proxylists
Author: Jesus Lara
Author-email: jesuslarag@gmail.com
License: BSD
Project-URL: Source, https://github.com/phenobarbital/proxylists
Project-URL: Tracker, https://github.com/phenobarbital/proxylists/issues
Project-URL: Documentation, https://github.com/phenobarbital/proxylists/
Project-URL: Funding, https://paypal.me/phenobarbital
Project-URL: Say Thanks!, https://saythanks.io/to/phenobarbital
Classifier: Development Status :: 4 - Beta
Classifier: Intended Audience :: Developers
Classifier: Topic :: Software Development :: Build Tools
Classifier: Programming Language :: Python :: 3.9
Classifier: Programming Language :: Python :: 3.10
Classifier: Programming Language :: Python :: 3.11
Classifier: Programming Language :: Python :: 3.12
Requires-Python: >=3.9.12
License-File: LICENSE
Requires-Dist: asyncio==3.4.3
Requires-Dist: uvloop>=0.19.0
Requires-Dist: aiohttp>=3.9.3
Requires-Dist: requests>=2.28.2
Requires-Dist: requests[socks]>=2.28.2
Requires-Dist: lxml>=4.6.0
